shippo/__init__.py
shippo/api_requestor.py
shippo/certificate_blacklist.py
shippo/config.py
shippo/error.py
shippo/http_client.py
shippo/resource.py
shippo/test/__init__.py
shippo/test/fixtures/address/test_create
shippo/test/fixtures/address/test_invalid_create
shippo/test/fixtures/address/test_invalid_retrieve
shippo/test/fixtures/address/test_invalid_validate
shippo/test/fixtures/address/test_list_all
shippo/test/fixtures/address/test_list_page_size
shippo/test/fixtures/address/test_retrieve
shippo/test/fixtures/address/test_validate
shippo/test/fixtures/batch/test_add
shippo/test/fixtures/batch/test_create
shippo/test/fixtures/batch/test_invalid_add
shippo/test/fixtures/batch/test_invalid_create
shippo/test/fixtures/batch/test_invalid_purchase
shippo/test/fixtures/batch/test_invalid_remove
shippo/test/fixtures/batch/test_invalid_retrieve
shippo/test/fixtures/batch/test_purchase
shippo/test/fixtures/batch/test_remove
shippo/test/fixtures/batch/test_retrieve
shippo/test/fixtures/customs-declaration/test_create
shippo/test/fixtures/customs-declaration/test_invalid_create
shippo/test/fixtures/customs-declaration/test_invalid_retrieve
shippo/test/fixtures/customs-declaration/test_list_all
shippo/test/fixtures/customs-declaration/test_list_page_size
shippo/test/fixtures/customs-declaration/test_retrieve
shippo/test/fixtures/customs-item/test_create
shippo/test/fixtures/customs-item/test_invalid_create
shippo/test/fixtures/customs-item/test_invalid_retrieve
shippo/test/fixtures/customs-item/test_list_all
shippo/test/fixtures/customs-item/test_list_page_size
shippo/test/fixtures/customs-item/test_retrieve
shippo/test/fixtures/manifest/test_create
shippo/test/fixtures/manifest/test_invalid_create
shippo/test/fixtures/manifest/test_invalid_retrieve
shippo/test/fixtures/manifest/test_list_all
shippo/test/fixtures/manifest/test_list_page_size
shippo/test/fixtures/manifest/test_retrieve
shippo/test/fixtures/order/test_create
shippo/test/fixtures/order/test_invalid_create
shippo_legacy-2.1.6.dist-info/LICENSE
shippo_legacy-2.1.6.dist-info/METADATA
shippo_legacy-2.1.6.dist-info/WHEEL
shippo_legacy-2.1.6.dist-info/RECORD
