Metadata-Version: 2.1
Name: shippo-legacy
Version: 2.1.6
Summary: Shipping API Python library (USPS, FedEx, UPS and more)
Home-page: https://github.com/rapid537/shippo-legacy.git
Author: rapid537
Author-email: rapid537@zoho.com
Requires-Python: >=3.6,<4.0
Classifier: License :: OSI Approved :: MIT License
Classifier: Operating System :: OS Independent
Classifier: Programming Language :: Python :: 3
Classifier: Programming Language :: Python :: 3.6
Classifier: Programming Language :: Python :: 3.7
Classifier: Programming Language :: Python :: 3.8
Classifier: Programming Language :: Python :: 3.9
Classifier: Programming Language :: Python :: 3.10
Classifier: Programming Language :: Python :: 3.11
Classifier: Programming Language :: Python :: 3.12
Requires-Dist: chardet (>=5.2.0,<6.0.0)
Requires-Dist: requests (>=2.31.0,<3.0.0)
Requires-Dist: simplejson (>=3.16.0,<=3.17.2)
